{
  "authorDailyContributionsMap": {
    "abnermtj": [
      {
        "date": "2020-08-20",
        "commitResults": [
          {
            "hash": "569941e1efe220e91145f4e81bb5a2c6b500cc8e",
            "messageTitle": "add greet functionality",
            "messageBody": "",
            "fileTypesAndContributionMap": {
              "java": {
                "insertions": 6,
                "deletions": 6
              },
              "md": {
                "insertions": 3,
                "deletions": 0
              }
            }
          }
        ]
      },
      {
        "date": "2020-08-26",
        "commitResults": [
          {
            "hash": "58b01ea129ce1c0590544b054d12562e454bc597",
            "messageTitle": "add echo functionality",
            "messageBody": "",
            "tags": [
              "Level-1"
            ],
            "fileTypesAndContributionMap": {
              "java": {
                "insertions": 21,
                "deletions": 0
              }
            }
          },
          {
            "hash": "d230588c80e611f8a795115182c010fb667b2435",
            "messageTitle": "add listing",
            "messageBody": "",
            "tags": [
              "Level-2"
            ],
            "fileTypesAndContributionMap": {
              "java": {
                "insertions": 39,
                "deletions": 7
              }
            }
          },
          {
            "hash": "9001c6d672dcc9f5a4fe00552803b990f82d2495",
            "messageTitle": "add finishing tasks",
            "messageBody": "",
            "tags": [
              "Level-3"
            ],
            "fileTypesAndContributionMap": {
              "java": {
                "insertions": 67,
                "deletions": 34
              }
            }
          },
          {
            "hash": "c5684ba811cdcf3ac3126b1e22ae96b764ff77ff",
            "messageTitle": "change code variable names",
            "messageBody": "",
            "tags": [
              "A-CodingStandard"
            ],
            "fileTypesAndContributionMap": {
              "java": {
                "insertions": 3,
                "deletions": 2
              }
            }
          }
        ]
      },
      {
        "date": "2020-09-01",
        "commitResults": [
          {
            "hash": "1d085299d025a8a7e80b6cd484a870556ae7a545",
            "messageTitle": "add new Task subclasses ToDos, Events, Deadlines",
            "messageBody": "",
            "tags": [
              "Level-4"
            ],
            "fileTypesAndContributionMap": {
              "java": {
                "insertions": 162,
                "deletions": 50
              }
            }
          },
          {
            "hash": "7d5a5499a988be26ca72333fe79877bbf4754fa4",
            "messageTitle": "add basic testing",
            "messageBody": "",
            "tags": [
              "A-TextUiTesting"
            ],
            "fileTypesAndContributionMap": {
              "txt": {
                "insertions": 13,
                "deletions": 0
              },
              "sh": {
                "insertions": 2,
                "deletions": 2
              }
            }
          },
          {
            "hash": "b81f997213f27419c9d051d806bb2b2191b92840",
            "messageTitle": "reduce linecount on verbose functions",
            "messageBody": "",
            "tags": [
              "A-CodeQuality"
            ],
            "fileTypesAndContributionMap": {
              "java": {
                "insertions": 39,
                "deletions": 22
              }
            }
          }
        ]
      },
      {
        "date": "2020-09-02",
        "commitResults": [
          {
            "hash": "54a7a824a80b0a1c30f9cc33606c6c781fd1f4e4",
            "messageTitle": "Fix Coding Standard violations",
            "messageBody": "",
            "fileTypesAndContributionMap": {
              "java": {
                "insertions": 26,
                "deletions": 23
              }
            }
          },
          {
            "hash": "36942761c6ba4d2426666fb339520e7597bee43d",
            "messageTitle": "fix formatting issues",
            "messageBody": "",
            "fileTypesAndContributionMap": {
              "java": {
                "insertions": 44,
                "deletions": 36
              }
            }
          }
        ]
      },
      {
        "date": "2020-09-03",
        "commitResults": [
          {
            "hash": "7857322b8988f76148f1fffe64f480555ccf36c1",
            "messageTitle": "refactor duke.java",
            "messageBody": "",
            "fileTypesAndContributionMap": {
              "java": {
                "insertions": 59,
                "deletions": 49
              }
            }
          }
        ]
      },
      {
        "date": "2020-09-08",
        "commitResults": [
          {
            "hash": "86b9bdb7aee8144167e65808b35940513932c65d",
            "messageTitle": "add DukeExceptions and handling",
            "messageBody": "",
            "fileTypesAndContributionMap": {
              "java": {
                "insertions": 84,
                "deletions": 83
              }
            }
          },
          {
            "hash": "6a05692839b9785d9afe3659deb48f49680824cf",
            "messageTitle": "created packages and updated testing",
            "messageBody": "",
            "fileTypesAndContributionMap": {
              "java": {
                "insertions": 20,
                "deletions": 6
              },
              "sh": {
                "insertions": 1,
                "deletions": 1
              }
            }
          }
        ]
      },
      {
        "date": "2020-09-14",
        "commitResults": [
          {
            "hash": "377ef1751eaa5cf74156d07e7bcf6dabfcba0f2d",
            "messageTitle": "add delete function",
            "messageBody": "",
            "tags": [
              "Level-6"
            ],
            "fileTypesAndContributionMap": {
              "java": {
                "insertions": 97,
                "deletions": 44
              }
            }
          },
          {
            "hash": "532842ee0db90a3b361432ee95446e6ed3e13a68",
            "messageTitle": "add save function",
            "messageBody": "",
            "tags": [
              "Level-7"
            ],
            "fileTypesAndContributionMap": {
              "java": {
                "insertions": 147,
                "deletions": 44
              }
            }
          }
        ]
      },
      {
        "date": "2020-09-16",
        "commitResults": [
          {
            "hash": "417a07085dac28379c774c27a78b7081fb31e648",
            "messageTitle": "refactor code",
            "messageBody": "",
            "fileTypesAndContributionMap": {
              "txt": {
                "insertions": 3,
                "deletions": 0
              },
              "java": {
                "insertions": 128,
                "deletions": 85
              }
            }
          }
        ]
      }
    ]
  },
  "authorFileTypeContributionMap": {
    "abnermtj": {
      "java": 421,
      "md": 3,
      "sh": 1,
      "bat": 0,
      "gradle": 0,
      "txt": 16
    }
  },
  "authorContributionVariance": {
    "abnermtj": 8086.5146
  },
  "authorDisplayNameMap": {
    "abnermtj": "CS2113T-W11-3 TOLE..ALES"
  }
}
